pycashier/__init__.py
pycashier/_checks.py
pycashier/_version.py
pycashier/cli.py
pycashier/config.py
pycashier/deps.py
pycashier/filters.py
pycashier/merge.py
pycashier/options.py
pycashier/pycashier.py
pycashier/receipt.py
pycashier/sample.py
pycashier/scrna.py
pycashier/term.py
pycashier/termui.py
pycashier/utils.py
pycashier-2024.1007.dist-info/LICENSE
pycashier-2024.1007.dist-info/METADATA
pycashier-2024.1007.dist-info/WHEEL
pycashier-2024.1007.dist-info/entry_points.txt
pycashier-2024.1007.dist-info/top_level.txt
pycashier-2024.1007.dist-info/RECORD
