Metadata-Version: 2.1
Name: pycashier
Version: 2024.1007
Summary: cash in on expressed barcode tags
Author-email: Daylin Morgan <daylinmorgan@gmail.com>
License: MIT
Project-URL: repository, https://github.com/brocklab/pycashier/
Project-URL: documentation, https://docs.brocklab.com/pycashier
Requires-Python: >=3.9
License-File: LICENSE
Requires-Dist: rich >=12.0.0
Requires-Dist: tomlkit >=0.10.1
Requires-Dist: click-rich-help >=22.1.0
Requires-Dist: click >=8.1.0
Requires-Dist: polars >=1.10.0
